<?xml version="1.0"?>
<!DOCTYPE hibernate-mapping PUBLIC "-//Hibernate/Hibernate Mapping DTD 3.0//EN"
"http://hibernate.sourceforge.net/hibernate-mapping-3.0.dtd">
<hibernate-mapping>
<class entity-name="BQ_SMTZ" table="BQ_SMTZ">
			<id name="CJH" type="java.lang.Long">
            	<column name="CJH"/>
            	<generator class="assigned" />
        	</id>
        	<property name="CJZH" type="java.lang.String" length="18" />
        	<property name="XMH" type="java.lang.String" length="18" />
        	<property name="JHBZ" type="java.lang.String" length="1" />
        	<property name="CJSJ" type="timestamp"  />
        	<property name="ZYH" type="java.lang.String" length="18" />
        	<property name="BRKS" type="java.lang.String" length="4" />
        	<property name="BRBQ" type="java.lang.String" length="4" />
        	<property name="BRCH" type="java.lang.String" length="6" />
        	<property name="TZNR" type="java.lang.String" length="60" />
        	<property name="XMXB" type="java.lang.String" length="20" />
        	<property name="FCBZ" type="java.lang.String" length="1" />
        	<property name="FCGL" type="java.lang.String" length="18" />
        	<property name="TWDXS" type="java.lang.String" length="1" />
        	<property name="JLSJ" type="timestamp"  />
        	<property name="JLGH" type="java.lang.String" length="10" />
        	<property name="ZFBZ" type="java.lang.String" length="1" />
        	<property name="BZXX" type="java.lang.String" length="255" />
        	<property name="YCBZ" type="java.lang.String" length="1" />
        	<property name="JGID" type="java.lang.String" length="20" />
</class>
</hibernate-mapping>